cubeviz/__init__.py
cubeviz/_internal_init.py
cubeviz/conftest.py
cubeviz/cubeviz.py
cubeviz/flux_equivalences.py
cubeviz/image_viewer.py
cubeviz/keyboard_shortcuts.py
cubeviz/layout.py
cubeviz/layout.ui
cubeviz/listener.py
cubeviz/messages.py
cubeviz/setup_package.py
cubeviz/startup.py
cubeviz/toolbar.py
cubeviz/controls/__init__.py
cubeviz/controls/flux_unit_registry.py
cubeviz/controls/flux_units.py
cubeviz/controls/flux_units_gui.py
cubeviz/controls/overlay.py
cubeviz/controls/registered_flux_units.yaml
cubeviz/controls/slice.py
cubeviz/controls/wavelengths.py
cubeviz/controls/tests/__init__.py
cubeviz/controls/tests/test_flux_units.py
cubeviz/controls/tests/test_slice_controller.py
cubeviz/controls/tests/test_wavelength_controller.py
cubeviz/data/README.rst
cubeviz/data/resources/contour_icon.png
cubeviz/data/resources/cubeviz_full_size_logo.png
cubeviz/data/resources/cubeviz_icon.png
cubeviz/data/resources/cubeviz_logo.png
cubeviz/data/ui/apply_operation.ui
cubeviz/data_factories/__init__.py
cubeviz/data_factories/ifucube.py
cubeviz/data_factories/ifucube_popup.ui
cubeviz/data_factories/configurations/cwi.yaml
cubeviz/data_factories/configurations/default.yaml
cubeviz/data_factories/configurations/flames.yaml
cubeviz/data_factories/configurations/gmos.yaml
cubeviz/data_factories/configurations/jwst-asdf.yaml
cubeviz/data_factories/configurations/jwst-fits.yaml
cubeviz/data_factories/configurations/kmos-other.yaml
cubeviz/data_factories/configurations/kmos.yaml
cubeviz/data_factories/configurations/manga.yaml
cubeviz/data_factories/configurations/muse.yaml
cubeviz/data_factories/configurations/pcwi.yaml
cubeviz/data_factories/configurations/sinfoni.yaml
cubeviz/data_factories/tests/__init__.py
cubeviz/data_factories/tests/test_data_factories.py
cubeviz/data_factories/tests/data/SINFONI_CAS64_k_bjames.fits
cubeviz/data_factories/tests/data/det_image_seq1_MIRIFUSHORT_12SHORTexp1_s3d.fits
cubeviz/data_factories/tests/data/manga-7495-12704-LOGCUBE.fits
cubeviz-0.3.3.dist-info/LICENSE.rst
cubeviz-0.3.3.dist-info/METADATA
cubeviz-0.3.3.dist-info/WHEEL
cubeviz-0.3.3.dist-info/entry_points.txt
cubeviz-0.3.3.dist-info/top_level.txt
cubeviz-0.3.3.dist-info/RECORD
