Metadata-Version: 2.1
Name: cubeviz
Version: 0.3.3
Summary: Data analysis package for cubes.
Home-page: https://github.com/spacetelescope/cubeviz
Author: JDADF Developers
License: BSD 3-Clause
Platform: UNKNOWN
Provides: cubeviz
Requires-Python: ==3.6.13
License-File: licenses/LICENSE.rst
Requires-Dist: pyqt5 (<5.12)
Requires-Dist: numpy (>=1.13)
Requires-Dist: matplotlib
Requires-Dist: astropy (==3.1)
Requires-Dist: asdf
Requires-Dist: glue-core (==0.14)
Requires-Dist: specviz (==0.7.0)
Requires-Dist: spectral-cube (<0.4.4)
